MANIFEST.in
setup.py
pyrailgun/__init__.py
pyrailgun/cwebbrowser.py
pyrailgun/logger.py
pyrailgun/logging.conf
pyrailgun/pattern.py
pyrailgun/railgun.py
pyrailgun.egg-info/PKG-INFO
pyrailgun.egg-info/SOURCES.txt
pyrailgun.egg-info/dependency_links.txt
pyrailgun.egg-info/requires.txt
pyrailgun.egg-info/top_level.txt