Metadata-Version: 1.1
Name: pyrailgun
Version: 0.26
Summary: Fast Crawler For Python
Home-page: https://github.com/princehaku/pyrailgun
Author: zhongwei bai
Author-email: baizhongwei@163.com
License: MIT
Download-URL: https://pypi.python.org/packages/source/P/pyrailgun/pyrailgun-0.26.tar.gz
Platform: Any
Classifier: Development Status :: 5 - Production/Stable
Classifier: Intended Audience :: Developers
Classifier: License :: OSI Approved :: MIT License
Classifier: Operating System :: OS Independent
Classifier: Programming Language :: Python :: 2.7
Classifier: Topic :: Internet :: WWW/HTTP :: Indexing/Search
Classifier: Topic :: Software Development :: Libraries :: Python Modules
